README.md
setup.py
dcos_deploy.egg-info/PKG-INFO
dcos_deploy.egg-info/SOURCES.txt
dcos_deploy.egg-info/dependency_links.txt
dcos_deploy.egg-info/entry_points.txt
dcos_deploy.egg-info/requires.txt
dcos_deploy.egg-info/top_level.txt
dcosdeploy/__init__.py
dcosdeploy/auth.py
dcosdeploy/base.py
dcosdeploy/delete.py
dcosdeploy/deploy.py
dcosdeploy/adapters/__init__.py
dcosdeploy/adapters/bouncer.py
dcosdeploy/adapters/ca.py
dcosdeploy/adapters/cosmos.py
dcosdeploy/adapters/dcos.py
dcosdeploy/adapters/edgelb.py
dcosdeploy/adapters/marathon.py
dcosdeploy/adapters/mesos.py
dcosdeploy/adapters/metronome.py
dcosdeploy/adapters/s3.py
dcosdeploy/adapters/secrets.py
dcosdeploy/commands/__init__.py
dcosdeploy/commands/all.py
dcosdeploy/commands/apply.py
dcosdeploy/commands/delete.py
dcosdeploy/commands/vault.py
dcosdeploy/commands/version.py
dcosdeploy/config/__init__.py
dcosdeploy/config/predefined.py
dcosdeploy/config/reader.py
dcosdeploy/config/variables.py
dcosdeploy/modules/__init__.py
dcosdeploy/modules/accounts.py
dcosdeploy/modules/apps.py
dcosdeploy/modules/certs.py
dcosdeploy/modules/edgelb.py
dcosdeploy/modules/frameworks.py
dcosdeploy/modules/httpcall.py
dcosdeploy/modules/iam_groups.py
dcosdeploy/modules/iam_users.py
dcosdeploy/modules/jobs.py
dcosdeploy/modules/marathon_groups.py
dcosdeploy/modules/repositories.py
dcosdeploy/modules/s3.py
dcosdeploy/modules/secrets.py
dcosdeploy/modules/taskexec.py
dcosdeploy/util/__init__.py
dcosdeploy/util/crypto.py
dcosdeploy/util/diff.py
dcosdeploy/util/file.py
dcosdeploy/util/global_config.py
dcosdeploy/util/http.py
dcosdeploy/util/output.py
dcosdeploy/util/script.py
dcosdeploy/util/vars.py