Metadata-Version: 2.1
Name: dcos-deploy
Version: 0.4.0
Summary: Deploy and orchestrate DC/OS services and apps
Home-page: https://github.com/MaibornWolff/dcos-deploy/
Author: MaibornWolff
License: Apache 2.0
Keywords: dcos marathon mesos
Platform: UNKNOWN
Classifier: License :: OSI Approved :: Apache Software License
Classifier: Environment :: Console
Classifier: Development Status :: 4 - Beta
Classifier: Programming Language :: Python :: 3
Classifier: Programming Language :: Python :: 3.5
Classifier: Programming Language :: Python :: 3.6
Classifier: Programming Language :: Python :: 3.7
Classifier: Programming Language :: Python :: 3.8
Requires-Python: >=3.5
